helpers/__init__.py
helpers/constants.py
ryobigdopy-0.0.1.dist-info/LICENSE
ryobigdopy-0.0.1.dist-info/METADATA
ryobigdopy-0.0.1.dist-info/WHEEL
ryobigdopy-0.0.1.dist-info/top_level.txt
ryobigdopy-0.0.1.dist-info/RECORD
