Metadata-Version: 2.1
Name: ryobigdopy
Version: 0.0.1
Summary: Library for communicating with Ryobi Garage Door Websocket and HTTP API.
Author-email: "chris@chriswood.org" <chris@chriswood.org>
License: # MIT License        
Project-URL: Homepage, https://github.com/CJOWood/ryobigdopy
Project-URL: Bug Tracker, https://github.com/CJOWood/ryobigdopy/issues
Classifier: Programming Language :: Python :: 3
Classifier: License :: OSI Approved :: MIT License
Classifier: Operating System :: OS Independent
Requires-Python: >=3.7
License-File: LICENSE
